gimmebio.data_manager-0.2.19-py3.6-nspkg.pth
gimmebio/data_manager/__init__.py
gimmebio/data_manager/api.py
gimmebio/data_manager/cli.py
gimmebio/data_manager/constants.py
gimmebio/data_manager/db.py
gimmebio/data_manager/models.py
gimmebio.data_manager-0.2.19.dist-info/METADATA
gimmebio.data_manager-0.2.19.dist-info/WHEEL
gimmebio.data_manager-0.2.19.dist-info/namespace_packages.txt
gimmebio.data_manager-0.2.19.dist-info/top_level.txt
gimmebio.data_manager-0.2.19.dist-info/RECORD
