Metadata-Version: 2.1
Name: gimmebio.data-manager
Version: 0.2.19
Summary: UNKNOWN
Home-page: UNKNOWN
Author: David Danko
Author-email: dcdanko@gmail.com
License: MIT license
Platform: UNKNOWN
Classifier: License :: OSI Approved :: MIT License
Classifier: Natural Language :: English
Classifier: Programming Language :: Python :: 3.6
Requires-Dist: pandas
Requires-Dist: click
Requires-Dist: boto3
Requires-Dist: sqlalchemy
